Workbook

Sheet Assumptions
A1: Marketplace financial model (BRL)
A2: Starting point: Olist actuals for 2018-08-01. Yellow cells are editable.
A4: Selected scenario | B4: Base
A5: Starting monthly orders | B5: 6421
A6: Starting AOV (BRL) | B6: 155.27
A8: Assumption | B8: Bear | C8: Base | D8: Bull | E8: Selected
A9: Monthly order growth | B9: 0.01 | C9: 0.03 | D9: 0.05 | E9: =INDEX(B9:D9,MATCH($B$4,$B$8:$D$8,0))
A10: Monthly AOV growth | B10: 0 | C10: 0.002 | D10: 0.004 | E10: =INDEX(B10:D10,MATCH($B$4,$B$8:$D$8,0))
A11: Take rate (commission on GMV) | B11: 0.1 | C11: 0.12 | D11: 0.14 | E11: =INDEX(B11:D11,MATCH($B$4,$B$8:$D$8,0))
A12: Payment + fraud cost (% of GMV) | B12: 0.025 | C12: 0.022 | D12: 0.02 | E12: =INDEX(B12:D12,MATCH($B$4,$B$8:$D$8,0))
A13: Share of orders from new customers | B13: 0.97 | C13: 0.95 | D13: 0.92 | E13: =INDEX(B13:D13,MATCH($B$4,$B$8:$D$8,0))
A14: CAC per new customer (BRL) | B14: 45 | C14: 35 | D14: 28 | E14: =INDEX(B14:D14,MATCH($B$4,$B$8:$D$8,0))
A15: Fixed costs per month (BRL) | B15: 450000 | C15: 420000 | D15: 400000 | E15: =INDEX(B15:D15,MATCH($B$4,$B$8:$D$8,0))
A16: Fixed cost growth per month | B16: 0.02 | C16: 0.015 | D16: 0.01 | E16: =INDEX(B16:D16,MATCH($B$4,$B$8:$D$8,0))
A17: Starting cash (BRL) | B17: 15000000 | C17: 15000000 | D17: 15000000 | E17: =INDEX(B17:D17,MATCH($B$4,$B$8:$D$8,0))

Sheet Model
A1: Month | B1: Orders | C1: AOV | D1: GMV | E1: Net revenue | F1: Payment costs | G1: New customers | H1: Marketing (CAC) | I1: Contribution | J1: Fixed costs | K1: EBITDA | L1: Cash (end)
A2: 1 | B2: =Assumptions!$B$5*(1+Assumptions!$E$9) | C2: =Assumptions!$B$6*(1+Assumptions!$E$10) | D2: =B2*C2 | E2: =D2*Assumptions!$E$11 | F2: =D2*Assumptions!$E$12 | G2: =B2*Assumptions!$E$13 | H2: =G2*Assumptions!$E$14 | I2: =E2-F2-H2 | J2: =Assumptions!$E$15 | K2: =I2-J2 | L2: =Assumptions!$E$17+K2
A3: 2 | B3: =B2*(1+Assumptions!$E$9) | C3: =C2*(1+Assumptions!$E$10) | D3: =B3*C3 | E3: =D3*Assumptions!$E$11 | F3: =D3*Assumptions!$E$12 | G3: =B3*Assumptions!$E$13 | H3: =G3*Assumptions!$E$14 | I3: =E3-F3-H3 | J3: =J2*(1+Assumptions!$E$16) | K3: =I3-J3 | L3: =L2+K3
A4: 3 | B4: =B3*(1+Assumptions!$E$9) | C4: =C3*(1+Assumptions!$E$10) | D4: =B4*C4 | E4: =D4*Assumptions!$E$11 | F4: =D4*Assumptions!$E$12 | G4: =B4*Assumptions!$E$13 | H4: =G4*Assumptions!$E$14 | I4: =E4-F4-H4 | J4: =J3*(1+Assumptions!$E$16) | K4: =I4-J4 | L4: =L3+K4
A5: 4 | B5: =B4*(1+Assumptions!$E$9) | C5: =C4*(1+Assumptions!$E$10) | D5: =B5*C5 | E5: =D5*Assumptions!$E$11 | F5: =D5*Assumptions!$E$12 | G5: =B5*Assumptions!$E$13 | H5: =G5*Assumptions!$E$14 | I5: =E5-F5-H5 | J5: =J4*(1+Assumptions!$E$16) | K5: =I5-J5 | L5: =L4+K5
A6: 5 | B6: =B5*(1+Assumptions!$E$9) | C6: =C5*(1+Assumptions!$E$10) | D6: =B6*C6 | E6: =D6*Assumptions!$E$11 | F6: =D6*Assumptions!$E$12 | G6: =B6*Assumptions!$E$13 | H6: =G6*Assumptions!$E$14 | I6: =E6-F6-H6 | J6: =J5*(1+Assumptions!$E$16) | K6: =I6-J6 | L6: =L5+K6
A7: 6 | B7: =B6*(1+Assumptions!$E$9) | C7: =C6*(1+Assumptions!$E$10) | D7: =B7*C7 | E7: =D7*Assumptions!$E$11 | F7: =D7*Assumptions!$E$12 | G7: =B7*Assumptions!$E$13 | H7: =G7*Assumptions!$E$14 | I7: =E7-F7-H7 | J7: =J6*(1+Assumptions!$E$16) | K7: =I7-J7 | L7: =L6+K7
A8: 7 | B8: =B7*(1+Assumptions!$E$9) | C8: =C7*(1+Assumptions!$E$10) | D8: =B8*C8 | E8: =D8*Assumptions!$E$11 | F8: =D8*Assumptions!$E$12 | G8: =B8*Assumptions!$E$13 | H8: =G8*Assumptions!$E$14 | I8: =E8-F8-H8 | J8: =J7*(1+Assumptions!$E$16) | K8: =I8-J8 | L8: =L7+K8
A9: 8 | B9: =B8*(1+Assumptions!$E$9) | C9: =C8*(1+Assumptions!$E$10) | D9: =B9*C9 | E9: =D9*Assumptions!$E$11 | F9: =D9*Assumptions!$E$12 | G9: =B9*Assumptions!$E$13 | H9: =G9*Assumptions!$E$14 | I9: =E9-F9-H9 | J9: =J8*(1+Assumptions!$E$16) | K9: =I9-J9 | L9: =L8+K9
A10: 9 | B10: =B9*(1+Assumptions!$E$9) | C10: =C9*(1+Assumptions!$E$10) | D10: =B10*C10 | E10: =D10*Assumptions!$E$11 | F10: =D10*Assumptions!$E$12 | G10: =B10*Assumptions!$E$13 | H10: =G10*Assumptions!$E$14 | I10: =E10-F10-H10 | J10: =J9*(1+Assumptions!$E$16) | K10: =I10-J10 | L10: =L9+K10
A11: 10 | B11: =B10*(1+Assumptions!$E$9) | C11: =C10*(1+Assumptions!$E$10) | D11: =B11*C11 | E11: =D11*Assumptions!$E$11 | F11: =D11*Assumptions!$E$12 | G11: =B11*Assumptions!$E$13 | H11: =G11*Assumptions!$E$14 | I11: =E11-F11-H11 | J11: =J10*(1+Assumptions!$E$16) | K11: =I11-J11 | L11: =L10+K11
A12: 11 | B12: =B11*(1+Assumptions!$E$9) | C12: =C11*(1+Assumptions!$E$10) | D12: =B12*C12 | E12: =D12*Assumptions!$E$11 | F12: =D12*Assumptions!$E$12 | G12: =B12*Assumptions!$E$13 | H12: =G12*Assumptions!$E$14 | I12: =E12-F12-H12 | J12: =J11*(1+Assumptions!$E$16) | K12: =I12-J12 | L12: =L11+K12
A13: 12 | B13: =B12*(1+Assumptions!$E$9) | C13: =C12*(1+Assumptions!$E$10) | D13: =B13*C13 | E13: =D13*Assumptions!$E$11 | F13: =D13*Assumptions!$E$12 | G13: =B13*Assumptions!$E$13 | H13: =G13*Assumptions!$E$14 | I13: =E13-F13-H13 | J13: =J12*(1+Assumptions!$E$16) | K13: =I13-J13 | L13: =L12+K13
A14: 13 | B14: =B13*(1+Assumptions!$E$9) | C14: =C13*(1+Assumptions!$E$10) | D14: =B14*C14 | E14: =D14*Assumptions!$E$11 | F14: =D14*Assumptions!$E$12 | G14: =B14*Assumptions!$E$13 | H14: =G14*Assumptions!$E$14 | I14: =E14-F14-H14 | J14: =J13*(1+Assumptions!$E$16) | K14: =I14-J14 | L14: =L13+K14
... A37: 36 | B37: =B36*(1+Assumptions!$E$9) | C37: =C36*(1+Assumptions!$E$10) | D37: =B37*C37 | E37: =D37*Assumptions!$E$11 | F37: =D37*Assumptions!$E$12 | G37: =B37*Assumptions!$E$13 | H37: =G37*Assumptions!$E$14 | I37: =E37-F37-H37 | J37: =J36*(1+Assumptions!$E$16) | K37: =I37-J37 | L37: =L36+K37

Sheet Summary
A1: Scenario | B1: =Assumptions!B4
A2: GMV, month 12 | B2: =Model!D13
A3: GMV, month 36 | B3: =Model!D37
A4: Contribution margin, month 12 | B4: =Model!I13/Model!E13
A5: First month with positive EBITDA | B5: =IFERROR(INDEX(Model!A2:A37,MATCH(TRUE,INDEX(Model!K2:K37>0,0),0)),"not within 36 months")
A6: Lowest cash balance | B6: =MIN(Model!L2:L37)
A7: Months of runway (cash > 0) | B7: =COUNTIF(Model!L2:L37,">0")
